portdatasplitter/__init__.py
portdatasplitter/functions.py
portdatasplitter/main.py
portdatasplitter/settings.py
portdatasplitter/tests/__init__.py
portdatasplitter/tests/main_test.py
portdatasplitter/tests/qpi_test.py
portdatasplitter/tests/server_tests.py
portdatasplitter/tests/setting_test_value_test.py
portdatasplitter/tests/test_functions.py
portdatasplitter/tests/test_settings.py
portdatasplitter-2.0.9.dist-info/LICENSE
portdatasplitter-2.0.9.dist-info/METADATA
portdatasplitter-2.0.9.dist-info/WHEEL
portdatasplitter-2.0.9.dist-info/top_level.txt
portdatasplitter-2.0.9.dist-info/RECORD
