Metadata-Version: 2.1
Name: portdatasplitter
Version: 2.0.9
Summary: UNKNOWN
Home-page: UNKNOWN
Author: PunchyArchy
Author-email: ksmdrmvscthny@gmail.com
License: UNKNOWN
Platform: UNKNOWN
License-File: LICENSE
Requires-Dist: pyserial
